st_event_selectioninterface/__init__.py
st_event_selectioninterface/frontend/build/asset-manifest.json
st_event_selectioninterface/frontend/build/bootstrap.min.css
st_event_selectioninterface/frontend/build/index.html
st_event_selectioninterface/frontend/build/precache-manifest.e9cab34e53db54fb6a9ecd4b68dc3af9.js
st_event_selectioninterface/frontend/build/service-worker.js
st_event_selectioninterface/frontend/build/static/js/2.524d9ab4.chunk.js
st_event_selectioninterface/frontend/build/static/js/2.524d9ab4.chunk.js.LICENSE.txt
st_event_selectioninterface/frontend/build/static/js/2.524d9ab4.chunk.js.map
st_event_selectioninterface/frontend/build/static/js/main.5677e1d7.chunk.js
st_event_selectioninterface/frontend/build/static/js/main.5677e1d7.chunk.js.map
st_event_selectioninterface/frontend/build/static/js/runtime-main.44d30fc2.js
st_event_selectioninterface/frontend/build/static/js/runtime-main.44d30fc2.js.map
st_event_selectioninterface-0.0.1.dist-info/LICENSE
st_event_selectioninterface-0.0.1.dist-info/METADATA
st_event_selectioninterface-0.0.1.dist-info/WHEEL
st_event_selectioninterface-0.0.1.dist-info/top_level.txt
st_event_selectioninterface-0.0.1.dist-info/RECORD
